<?xml version="1.0" encoding="UTF-8"?>
<xbrli:xbrl xmlns:in-bse-fin="http://www.bseindia.com/xbrl/fin/2020-03-31/in-bse-fin" xmlns:in-bse-fin-roles="http://www.bseindia.com/xbrl/fin/2020-03-31/in-bse-fin-roles" xmlns:in-bse-fin-ent="http://www.bseindia.com/xbrl/fin/2020-03-31/in-bse-fin/in-bse-fin-ent" xmlns:in-bse-fin-type="http://www.bseindia.com/xbrl/fin/2020-03-31/in-bse-fin-types" xmlns:xbrldt="http://xbrl.org/2005/xbrldt" xmlns:nonnum="http://www.xbrl.org/dtr/type/non-numeric" xmlns:link="http://www.xbrl.org/2003/linkbase" xmlns:net="http://www.xbrl.org/2009/role/net" xmlns:num="http://www.xbrl.org/dtr/type/numeric" xmlns:xlink="http://www.w3.org/1999/xlink" xmlns:iso4217="http://www.xbrl.org/2003/iso4217" xmlns:negated="http://www.xbrl.org/2009/role/negated" xmlns:xbrldi="http://xbrl.org/2006/xbrldi" xmlns:xbrli="http://www.xbrl.org/2003/instance" xmlns:xl="http://www.xbrl.org/2003/XLink">
<link:schemaRef xlink:type="simple" xlink:href="Ind-AS_entry_point_2020-03-31.xsd"/>
<xbrli:context id="OneOperatingExpenses01D"><xbrli:entity><xbrli:identifier scheme="http://www.nseindia.com/NSESymbol">HEROMOTOCO</xbrli:identifier></xbrli:entity><xbrli:period><xbrli:startDate>2020-07-01</xbrli:startDate><xbrli:endDate>2020-09-30</xbrli:endDate></xbrli:period><xbrli:scenario><xbrldi:explicitMember dimension="in-bse-fin:DetailsOfOtherExpensesAxis">in-bse-fin:OneOperatingExpenses01Member</xbrldi:explicitMember></xbrli:scenario></xbrli:context>
<xbrli:context id="FourOperatingExpenses01D"><xbrli:entity><xbrli:identifier scheme="http://www.nseindia.com/NSESymbol">HEROMOTOCO</xbrli:identifier></xbrli:entity><xbrli:period><xbrli:startDate>2020-07-01</xbrli:startDate><xbrli:endDate>2020-09-30</xbrli:endDate></xbrli:period><xbrli:scenario><xbrldi:explicitMember dimension="in-bse-fin:DetailsOfOtherExpensesAxis">in-bse-fin:FourOperatingExpenses01Member</xbrldi:explicitMember></xbrli:scenario></xbrli:context>
<xbrli:context id="OneItemsThatWillNotBeReclassifiedToProfitAndLoss01D"><xbrli:entity><xbrli:identifier scheme="http://www.nseindia.com/NSESymbol">HEROMOTOCO</xbrli:identifier></xbrli:entity><xbrli:period><xbrli:startDate>2020-07-01</xbrli:startDate><xbrli:endDate>2020-09-30</xbrli:endDate></xbrli:period><xbrli:scenario><xbrldi:typedMember dimension="in-bse-fin:ItemsThatWillNotBeReclassifiedToProfitAndLossAxis"><ItemsThatWillNotBeReclassifiedToProfitAndLossDomain>in-bse-fin:OneItemsThatWillNotBeReclassifiedToProfitAndLoss01Member</ItemsThatWillNotBeReclassifiedToProfitAndLossDomain></xbrldi:typedMember></xbrli:scenario></xbrli:context>
<xbrli:context id="FourItemsThatWillNotBeReclassifiedToProfitAndLoss01D"><xbrli:entity><xbrli:identifier scheme="http://www.nseindia.com/NSESymbol">HEROMOTOCO</xbrli:identifier></xbrli:entity><xbrli:period><xbrli:startDate>2020-07-01</xbrli:startDate><xbrli:endDate>2020-09-30</xbrli:endDate></xbrli:period><xbrli:scenario><xbrldi:typedMember dimension="in-bse-fin:ItemsThatWillNotBeReclassifiedToProfitAndLossAxis"><ItemsThatWillNotBeReclassifiedToProfitAndLossDomain>in-bse-fin:FourItemsThatWillNotBeReclassifiedToProfitAndLoss01Member</ItemsThatWillNotBeReclassifiedToProfitAndLossDomain></xbrldi:typedMember></xbrli:scenario></xbrli:context>
<xbrli:context id="OneItemsThatWillBeReclassifiedToProfitAndLoss01D"><xbrli:entity><xbrli:identifier scheme="http://www.nseindia.com/NSESymbol">HEROMOTOCO</xbrli:identifier></xbrli:entity><xbrli:period><xbrli:startDate>2020-07-01</xbrli:startDate><xbrli:endDate>2020-09-30</xbrli:endDate></xbrli:period><xbrli:scenario><xbrldi:typedMember dimension="in-bse-fin:ItemsThatWillBeReclassifiedToProfitAndLossAxis"><ItemsThatWillBeReclassifiedToProfitAndLossDomain>in-bse-fin:OneItemsThatWillBeReclassifiedToProfitAndLoss01Member</ItemsThatWillBeReclassifiedToProfitAndLossDomain></xbrldi:typedMember></xbrli:scenario></xbrli:context>
<xbrli:context id="FourItemsThatWillBeReclassifiedToProfitAndLoss01D"><xbrli:entity><xbrli:identifier scheme="http://www.nseindia.com/NSESymbol">HEROMOTOCO</xbrli:identifier></xbrli:entity><xbrli:period><xbrli:startDate>2020-07-01</xbrli:startDate><xbrli:endDate>2020-09-30</xbrli:endDate></xbrli:period><xbrli:scenario><xbrldi:typedMember dimension="in-bse-fin:ItemsThatWillBeReclassifiedToProfitAndLossAxis"><ItemsThatWillBeReclassifiedToProfitAndLossDomain>in-bse-fin:FourItemsThatWillBeReclassifiedToProfitAndLoss01Member</ItemsThatWillBeReclassifiedToProfitAndLossDomain></xbrldi:typedMember></xbrli:scenario></xbrli:context>
<xbrli:unit id="INR"><xbrli:measure>iso4217:INR</xbrli:measure></xbrli:unit><xbrli:unit id="pure"><xbrli:measure>xbrli:pure</xbrli:measure></xbrli:unit><xbrli:unit id="shares"><xbrli:measure>xbrli:shares</xbrli:measure></xbrli:unit><xbrli:unit id="INRPerShare"><xbrli:divide><xbrli:unitNumerator><xbrli:measure>iso4217:INR</xbrli:measure></xbrli:unitNumerator><xbrli:unitDenominator><xbrli:measure>xbrli:shares</xbrli:measure></xbrli:unitDenominator></xbrli:divide></xbrli:unit>
<in-bse-fin:Symbol contextRef="OneD">HEROMOTOCO</in-bse-fin:Symbol>
<in-bse-fin:DateOfStartOfFinancialYear contextRef="OneD">2020-04-01</in-bse-fin:DateOfStartOfFinancialYear>
<in-bse-fin:DateOfEndOfFinancialYear contextRef="OneD">2021-03-31</in-bse-fin:DateOfEndOfFinancialYear>
<in-bse-fin:DateOnWhichPriorIntimationOfTheMeetingForConsideringFinancialResultsWasInformedToTheExchange contextRef="OneD">2020-10-02</in-bse-fin:DateOnWhichPriorIntimationOfTheMeetingForConsideringFinancialResultsWasInformedToTheExchange>
<in-bse-fin:DescriptionOfPresentationCurrency contextRef="OneD">INR</in-bse-fin:DescriptionOfPresentationCurrency>
<in-bse-fin:LevelOfRoundingUsedInFinancialStatements contextRef="OneD">Crores</in-bse-fin:LevelOfRoundingUsedInFinancialStatements>
<in-bse-fin:ReportingQuarter contextRef="OneD">Half yearly</in-bse-fin:ReportingQuarter>
<in-bse-fin:WhetherCashFlowStatementIsApplicableOnCompany contextRef="OneD">true</in-bse-fin:WhetherCashFlowStatementIsApplicableOnCompany>
<in-bse-fin:TypeOfCashFlowStatement contextRef="OneD">Cash Flow Indirect</in-bse-fin:TypeOfCashFlowStatement>
<in-bse-fin:IsCompanyReportingMultisegmentOrSingleSegment contextRef="OneD">Single segment</in-bse-fin:IsCompanyReportingMultisegmentOrSingleSegment>
<in-bse-fin:DescriptionOfSingleSegment contextRef="OneD">Automotive Segment</in-bse-fin:DescriptionOfSingleSegment>
<in-bse-fin:DateOfStartOfReportingPeriod contextRef="OneD">2020-07-01</in-bse-fin:DateOfStartOfReportingPeriod>
<in-bse-fin:DateOfEndOfReportingPeriod contextRef="OneD">2020-09-30</in-bse-fin:DateOfEndOfReportingPeriod>
<in-bse-fin:WhetherResultsAreAuditedOrUnaudited contextRef="OneD">Unaudited</in-bse-fin:WhetherResultsAreAuditedOrUnaudited>
<in-bse-fin:NatureOfReportStandaloneConsolidated contextRef="OneD">Consolidated</in-bse-fin:NatureOfReportStandaloneConsolidated>
<in-bse-fin:RevenueFromOperations contextRef="OneD" unitRef="INR" decimals="-7">94733200000.00</in-bse-fin:RevenueFromOperations>
<in-bse-fin:OtherIncome contextRef="OneD" unitRef="INR" decimals="-7">1339300000.00</in-bse-fin:OtherIncome>
<in-bse-fin:Income contextRef="OneD" unitRef="INR" decimals="-7">96072500000.00</in-bse-fin:Income>
<in-bse-fin:CostOfMaterialsConsumed contextRef="OneD" unitRef="INR" decimals="-7">66923800000.00</in-bse-fin:CostOfMaterialsConsumed>
<in-bse-fin:PurchasesOfStockInTrade contextRef="OneD" unitRef="INR" decimals="-7">0.00</in-bse-fin:PurchasesOfStockInTrade>
<in-bse-fin:ChangesInInventoriesOfFinishedGoodsWorkInProgressAndStockInTrade contextRef="OneD" unitRef="INR" decimals="-7">263400000.00</in-bse-fin:ChangesInInventoriesOfFinishedGoodsWorkInProgressAndStockInTrade>
<in-bse-fin:EmployeeBenefitExpense contextRef="OneD" unitRef="INR" decimals="-7">5239800000.00</in-bse-fin:EmployeeBenefitExpense>
<in-bse-fin:FinanceCosts contextRef="OneD" unitRef="INR" decimals="-7">107100000.00</in-bse-fin:FinanceCosts>
<in-bse-fin:DepreciationDepletionAndAmortisationExpense contextRef="OneD" unitRef="INR" decimals="-7">1834600000.00</in-bse-fin:DepreciationDepletionAndAmortisationExpense>
<in-bse-fin:OtherExpenses contextRef="OneD" unitRef="INR" decimals="-7">9223600000.00</in-bse-fin:OtherExpenses>
<in-bse-fin:Expenses contextRef="OneD" unitRef="INR" decimals="-7">83592300000.00</in-bse-fin:Expenses>
<in-bse-fin:ProfitBeforeExceptionalItemsAndTax contextRef="OneD" unitRef="INR" decimals="-7">12480200000.00</in-bse-fin:ProfitBeforeExceptionalItemsAndTax>
<in-bse-fin:ExceptionalItemsBeforeTax contextRef="OneD" unitRef="INR" decimals="-7">0.00</in-bse-fin:ExceptionalItemsBeforeTax>
<in-bse-fin:ProfitBeforeTax contextRef="OneD" unitRef="INR" decimals="-7">12480200000.00</in-bse-fin:ProfitBeforeTax>
<in-bse-fin:CurrentTax contextRef="OneD" unitRef="INR" decimals="-7">2566500000.00</in-bse-fin:CurrentTax>
<in-bse-fin:DeferredTax contextRef="OneD" unitRef="INR" decimals="-7">405200000.00</in-bse-fin:DeferredTax>
<in-bse-fin:TaxExpense contextRef="OneD" unitRef="INR" decimals="-7">2971700000.00</in-bse-fin:TaxExpense>
<in-bse-fin:NetMovementInRegulatoryDeferralAccountBalancesRelatedToProfitOrLossAndTheRelatedDeferredTaxMovement contextRef="OneD" unitRef="INR" decimals="-7">0.00</in-bse-fin:NetMovementInRegulatoryDeferralAccountBalancesRelatedToProfitOrLossAndTheRelatedDeferredTaxMovement>
<in-bse-fin:ProfitLossForPeriodFromContinuingOperations contextRef="OneD" unitRef="INR" decimals="-7">9508500000.00</in-bse-fin:ProfitLossForPeriodFromContinuingOperations>
<in-bse-fin:ProfitLossFromDiscontinuedOperationsBeforeTax contextRef="OneD" unitRef="INR" decimals="-7">0.00</in-bse-fin:ProfitLossFromDiscontinuedOperationsBeforeTax>
<in-bse-fin:TaxExpenseOfDiscontinuedOperations contextRef="OneD" unitRef="INR" decimals="-7">0.00</in-bse-fin:TaxExpenseOfDiscontinuedOperations>
<in-bse-fin:ProfitLossFromDiscontinuedOperationsAfterTax contextRef="OneD" unitRef="INR" decimals="-7">0.00</in-bse-fin:ProfitLossFromDiscontinuedOperationsAfterTax>
<in-bse-fin:ShareOfProfitLossOfAssociatesAndJointVenturesAccountedForUsingEquityMethod contextRef="OneD" unitRef="INR" decimals="-7">129700000.00</in-bse-fin:ShareOfProfitLossOfAssociatesAndJointVenturesAccountedForUsingEquityMethod>
<in-bse-fin:ProfitLossForPeriod contextRef="OneD" unitRef="INR" decimals="-7">9638200000.00</in-bse-fin:ProfitLossForPeriod>
<in-bse-fin:OtherComprehensiveIncomeNetOfTaxes contextRef="OneD" unitRef="INR" decimals="-7">-150800000.00</in-bse-fin:OtherComprehensiveIncomeNetOfTaxes>
<in-bse-fin:ComprehensiveIncomeForThePeriod contextRef="OneD" unitRef="INR" decimals="-7">9487400000.00</in-bse-fin:ComprehensiveIncomeForThePeriod>
<in-bse-fin:ProfitOrLossAttributableToOwnersOfParent contextRef="OneD" unitRef="INR" decimals="-7">9584900000.00</in-bse-fin:ProfitOrLossAttributableToOwnersOfParent>
<in-bse-fin:ProfitOrLossAttributableToNonControllingInterests contextRef="OneD" unitRef="INR" decimals="-7">53300000.00</in-bse-fin:ProfitOrLossAttributableToNonControllingInterests>
<in-bse-fin:ComprehensiveIncomeForThePeriodAttributableToOwnersOfParent contextRef="OneD" unitRef="INR" decimals="-7">9460300000.00</in-bse-fin:ComprehensiveIncomeForThePeriodAttributableToOwnersOfParent>
<in-bse-fin:ComprehensiveIncomeForThePeriodAttributableToOwnersOfParentNonControllingInterests contextRef="OneD" unitRef="INR" decimals="-7">27100000.00</in-bse-fin:ComprehensiveIncomeForThePeriodAttributableToOwnersOfParentNonControllingInterests>
<in-bse-fin:PaidUpValueOfEquityShareCapital contextRef="OneD" unitRef="INR" decimals="-7">399500000.00</in-bse-fin:PaidUpValueOfEquityShareCapital>
<in-bse-fin:FaceValueOfEquityShareCapital contextRef="OneD" unitRef="INRPerShare" decimals="INF">2</in-bse-fin:FaceValueOfEquityShareCapital>
<in-bse-fin:BasicEarningsLossPerShareFromContinuingOperations contextRef="OneD" unitRef="INRPerShare" decimals="INF">47.99</in-bse-fin:BasicEarningsLossPerShareFromContinuingOperations>
<in-bse-fin:DilutedEarningsLossPerShareFromContinuingOperations contextRef="OneD" unitRef="INRPerShare" decimals="INF">47.98</in-bse-fin:DilutedEarningsLossPerShareFromContinuingOperations>
<in-bse-fin:BasicEarningsLossPerShareFromDiscontinuedOperations contextRef="OneD" unitRef="INRPerShare" decimals="INF">0.00</in-bse-fin:BasicEarningsLossPerShareFromDiscontinuedOperations>
<in-bse-fin:DilutedEarningsLossPerShareFromDiscontinuedOperations contextRef="OneD" unitRef="INRPerShare" decimals="INF">0.00</in-bse-fin:DilutedEarningsLossPerShareFromDiscontinuedOperations>
<in-bse-fin:BasicEarningsLossPerShareFromContinuingAndDiscontinuedOperations contextRef="OneD" unitRef="INRPerShare" decimals="INF">47.99</in-bse-fin:BasicEarningsLossPerShareFromContinuingAndDiscontinuedOperations>
<in-bse-fin:DilutedEarningsLossPerShareFromContinuingAndDiscontinuedOperations contextRef="OneD" unitRef="INRPerShare" decimals="INF">47.98</in-bse-fin:DilutedEarningsLossPerShareFromContinuingAndDiscontinuedOperations>
<in-bse-fin:DisclosureOfNotesOnFinancialResultsExplanatoryTextBlock contextRef="OneD">Notes:-  n  n1. The above unaudited consolidated financial results for the quarter and half year ended September 30, 2020 have been reviewed and recommended by the Audit Committee and approved by the Board of Directors in their respective meetings held on October 28, 2020. These results have been subjected to limited review by the statutory auditors.  n  n2. During the quarter ended September 30, 2020 , the Company has invested Rs. 84.00 crores as part of capital contribution in associate company i.e. Ather Energy Private Limited taking cumulative investment to Rs. 414.58 crores.  n  n3. On June 9, 2020, the Board of Directors had recommended a final dividend of Rs. 25 per equity share (face value of Rs.2 per equity share) for the financial year ended March 31, 2020, which has been approved by the shareholders in the Annual General Meeting held on August 12, 2020. Accordingly, Rs.499.35 crores was appropriated as distribution to equity shareholders during the quarter ended September 30, 2020.  n  n4. During the quarter ended September 30, 2020, 8,481 equity shares of Rs. 2 each were issued and allotted under the Employee Incentive Scheme – 2014.  n  n5. Based on the guiding principles given in Ind AS-108 on 'Operating Segments', the Group business activity fall within a single operating segment, namely automotive segment. Accordingly, the disclosure requirements of  Ind AS 108 are not applicable.  n  n6. Particulars of subsidiaries and associates as on September 30, 2020  n  na) Subsidiaries (held directly) - HMCL Netherlands B.V., HMC MM Auto Limited, HMCL Americas Inc., Hero TechCenter Germany GmbH  nb) Subsidiaries (held indirectly) - HMCL Colombia S.A.S., HMCL Niloy Bangladesh Limited (subsidiaries of HMCL Netherlands B.V.)  nc) Associates - Hero FinCorp Limited and Ather Energy Private Limited  n  n7. The Group's operations and financial results for the quarter ended June 30, 2020 were adversely impacted by the outbreak of COVID-19 pandemic and the consequent lockdown in various geographies. The operations have resumed with requisite precautions in place. The situation is continuously evolving, the impact assessed may be different from the estimates made as at the date of approval of these financial results and management will continue to monitor any material changes arising due to the impact of this pandemic on financial and operational performance of the Group and take necessary measures to address the situation.  n  n8. The above consolidated financial results of the Group are available on the Company's website www.heromotocorp.com and also on www.bseindia.com and www.nseindia.com</in-bse-fin:DisclosureOfNotesOnFinancialResultsExplanatoryTextBlock>
<in-bse-fin:IsCompanyReportingMultisegmentOrSingleSegment contextRef="FourD">Single segment</in-bse-fin:IsCompanyReportingMultisegmentOrSingleSegment>
<in-bse-fin:DateOfStartOfReportingPeriod contextRef="FourD">2020-04-01</in-bse-fin:DateOfStartOfReportingPeriod>
<in-bse-fin:DateOfEndOfReportingPeriod contextRef="FourD">2020-09-30</in-bse-fin:DateOfEndOfReportingPeriod>
<in-bse-fin:WhetherResultsAreAuditedOrUnaudited contextRef="FourD">Unaudited</in-bse-fin:WhetherResultsAreAuditedOrUnaudited>
<in-bse-fin:NatureOfReportStandaloneConsolidated contextRef="FourD">Consolidated</in-bse-fin:NatureOfReportStandaloneConsolidated>
<in-bse-fin:RevenueFromOperations contextRef="FourD" unitRef="INR" decimals="-7">124424000000.00</in-bse-fin:RevenueFromOperations>
<in-bse-fin:OtherIncome contextRef="FourD" unitRef="INR" decimals="-7">2840700000.00</in-bse-fin:OtherIncome>
<in-bse-fin:Income contextRef="FourD" unitRef="INR" decimals="-7">127264700000.00</in-bse-fin:Income>
<in-bse-fin:CostOfMaterialsConsumed contextRef="FourD" unitRef="INR" decimals="-7">85881600000.00</in-bse-fin:CostOfMaterialsConsumed>
<in-bse-fin:PurchasesOfStockInTrade contextRef="FourD" unitRef="INR" decimals="-7">0.00</in-bse-fin:PurchasesOfStockInTrade>
<in-bse-fin:ChangesInInventoriesOfFinishedGoodsWorkInProgressAndStockInTrade contextRef="FourD" unitRef="INR" decimals="-7">1918500000.00</in-bse-fin:ChangesInInventoriesOfFinishedGoodsWorkInProgressAndStockInTrade>
<in-bse-fin:EmployeeBenefitExpense contextRef="FourD" unitRef="INR" decimals="-7">9167600000.00</in-bse-fin:EmployeeBenefitExpense>
<in-bse-fin:FinanceCosts contextRef="FourD" unitRef="INR" decimals="-7">229000000.00</in-bse-fin:FinanceCosts>
<in-bse-fin:DepreciationDepletionAndAmortisationExpense contextRef="FourD" unitRef="INR" decimals="-7">3620000000.00</in-bse-fin:DepreciationDepletionAndAmortisationExpense>
<in-bse-fin:OtherExpenses contextRef="FourD" unitRef="INR" decimals="-7">13203100000.00</in-bse-fin:OtherExpenses>
<in-bse-fin:Expenses contextRef="FourD" unitRef="INR" decimals="-7">114019800000.00</in-bse-fin:Expenses>
<in-bse-fin:ProfitBeforeExceptionalItemsAndTax contextRef="FourD" unitRef="INR" decimals="-7">13244900000.00</in-bse-fin:ProfitBeforeExceptionalItemsAndTax>
<in-bse-fin:ExceptionalItemsBeforeTax contextRef="FourD" unitRef="INR" decimals="-7">0.00</in-bse-fin:ExceptionalItemsBeforeTax>
<in-bse-fin:ProfitBeforeTax contextRef="FourD" unitRef="INR" decimals="-7">13244900000.00</in-bse-fin:ProfitBeforeTax>
<in-bse-fin:CurrentTax contextRef="FourD" unitRef="INR" decimals="-7">2738300000.00</in-bse-fin:CurrentTax>
<in-bse-fin:DeferredTax contextRef="FourD" unitRef="INR" decimals="-7">434300000.00</in-bse-fin:DeferredTax>
<in-bse-fin:TaxExpense contextRef="FourD" unitRef="INR" decimals="-7">3172600000.00</in-bse-fin:TaxExpense>
<in-bse-fin:NetMovementInRegulatoryDeferralAccountBalancesRelatedToProfitOrLossAndTheRelatedDeferredTaxMovement contextRef="FourD" unitRef="INR" decimals="-7">0.00</in-bse-fin:NetMovementInRegulatoryDeferralAccountBalancesRelatedToProfitOrLossAndTheRelatedDeferredTaxMovement>
<in-bse-fin:ProfitLossForPeriodFromContinuingOperations contextRef="FourD" unitRef="INR" decimals="-7">10072300000.00</in-bse-fin:ProfitLossForPeriodFromContinuingOperations>
<in-bse-fin:ProfitLossFromDiscontinuedOperationsBeforeTax contextRef="FourD" unitRef="INR" decimals="-7">0.00</in-bse-fin:ProfitLossFromDiscontinuedOperationsBeforeTax>
<in-bse-fin:TaxExpenseOfDiscontinuedOperations contextRef="FourD" unitRef="INR" decimals="-7">0.00</in-bse-fin:TaxExpenseOfDiscontinuedOperations>
<in-bse-fin:ProfitLossFromDiscontinuedOperationsAfterTax contextRef="FourD" unitRef="INR" decimals="-7">0.00</in-bse-fin:ProfitLossFromDiscontinuedOperationsAfterTax>
<in-bse-fin:ShareOfProfitLossOfAssociatesAndJointVenturesAccountedForUsingEquityMethod contextRef="FourD" unitRef="INR" decimals="-7">143700000.00</in-bse-fin:ShareOfProfitLossOfAssociatesAndJointVenturesAccountedForUsingEquityMethod>
<in-bse-fin:ProfitLossForPeriod contextRef="FourD" unitRef="INR" decimals="-7">10216000000.00</in-bse-fin:ProfitLossForPeriod>
<in-bse-fin:OtherComprehensiveIncomeNetOfTaxes contextRef="FourD" unitRef="INR" decimals="-7">-195900000.00</in-bse-fin:OtherComprehensiveIncomeNetOfTaxes>
<in-bse-fin:ComprehensiveIncomeForThePeriod contextRef="FourD" unitRef="INR" decimals="-7">10020100000.00</in-bse-fin:ComprehensiveIncomeForThePeriod>
<in-bse-fin:ProfitOrLossAttributableToOwnersOfParent contextRef="FourD" unitRef="INR" decimals="-7">10176300000.00</in-bse-fin:ProfitOrLossAttributableToOwnersOfParent>
<in-bse-fin:ProfitOrLossAttributableToNonControllingInterests contextRef="FourD" unitRef="INR" decimals="-7">39700000.00</in-bse-fin:ProfitOrLossAttributableToNonControllingInterests>
<in-bse-fin:ComprehensiveIncomeForThePeriodAttributableToOwnersOfParent contextRef="FourD" unitRef="INR" decimals="-7">9994700000.00</in-bse-fin:ComprehensiveIncomeForThePeriodAttributableToOwnersOfParent>
<in-bse-fin:ComprehensiveIncomeForThePeriodAttributableToOwnersOfParentNonControllingInterests contextRef="FourD" unitRef="INR" decimals="-7">25400000.00</in-bse-fin:ComprehensiveIncomeForThePeriodAttributableToOwnersOfParentNonControllingInterests>
<in-bse-fin:PaidUpValueOfEquityShareCapital contextRef="FourD" unitRef="INR" decimals="-7">399500000.00</in-bse-fin:PaidUpValueOfEquityShareCapital>
<in-bse-fin:FaceValueOfEquityShareCapital contextRef="FourD" unitRef="INRPerShare" decimals="INF">2</in-bse-fin:FaceValueOfEquityShareCapital>
<in-bse-fin:BasicEarningsLossPerShareFromContinuingOperations contextRef="FourD" unitRef="INRPerShare" decimals="INF">50.95</in-bse-fin:BasicEarningsLossPerShareFromContinuingOperations>
<in-bse-fin:DilutedEarningsLossPerShareFromContinuingOperations contextRef="FourD" unitRef="INRPerShare" decimals="INF">50.94</in-bse-fin:DilutedEarningsLossPerShareFromContinuingOperations>
<in-bse-fin:BasicEarningsLossPerShareFromDiscontinuedOperations contextRef="FourD" unitRef="INRPerShare" decimals="INF">0.00</in-bse-fin:BasicEarningsLossPerShareFromDiscontinuedOperations>
<in-bse-fin:DilutedEarningsLossPerShareFromDiscontinuedOperations contextRef="FourD" unitRef="INRPerShare" decimals="INF">0.00</in-bse-fin:DilutedEarningsLossPerShareFromDiscontinuedOperations>
<in-bse-fin:BasicEarningsLossPerShareFromContinuingAndDiscontinuedOperations contextRef="FourD" unitRef="INRPerShare" decimals="INF">50.95</in-bse-fin:BasicEarningsLossPerShareFromContinuingAndDiscontinuedOperations>
<in-bse-fin:DilutedEarningsLossPerShareFromContinuingAndDiscontinuedOperations contextRef="FourD" unitRef="INRPerShare" decimals="INF">50.94</in-bse-fin:DilutedEarningsLossPerShareFromContinuingAndDiscontinuedOperations>
<in-bse-fin:DescriptionOfOtherExpenses contextRef="OneOperatingExpenses01D">Other Expenses</in-bse-fin:DescriptionOfOtherExpenses>
<in-bse-fin:OtherExpenses contextRef="OneOperatingExpenses01D" unitRef="INR" decimals="-7">9223600000.00</in-bse-fin:OtherExpenses>
<in-bse-fin:DescriptionOfOtherExpenses contextRef="FourOperatingExpenses01D">Other Expenses</in-bse-fin:DescriptionOfOtherExpenses>
<in-bse-fin:OtherExpenses contextRef="FourOperatingExpenses01D" unitRef="INR" decimals="-7">13203100000.00</in-bse-fin:OtherExpenses>
</xbrli:xbrl>